MANIFEST.in
README.md
aiocv/__init__.py
aiocv/car_detection_module.py
aiocv/contour_detection_module.py
aiocv/eyes_detection_module.py
aiocv/face_detection_module.py
aiocv/face_mesh_module.py
aiocv/gesture_volume_control_module.py
aiocv/hand_track_module.py
aiocv/number_plate_detection_module.py
aiocv/pose_track_module.py
aiocv/qr_code_reader_module.py
aiocv/smile_detection_module.py
aiocv.egg-info/PKG-INFO
aiocv.egg-info/SOURCES.txt
aiocv.egg-info/dependency_links.txt
aiocv.egg-info/requires.txt
aiocv.egg-info/top_level.txt
haarcascades/haarcascade_car.xml
haarcascades/haarcascade_eye.xml
haarcascades/haarcascade_russian_plate_number.xml
haarcascades/haarcascade_smile.xml
aiocv-0.0.36.dist-info/LICENCE.txt
aiocv-0.0.36.dist-info/METADATA
aiocv-0.0.36.dist-info/WHEEL
aiocv-0.0.36.dist-info/top_level.txt
aiocv-0.0.36.dist-info/RECORD
