Metadata-Version: 2.1
Name: aiocv
Version: 0.0.36
Summary: aiocv Is A Python Library Used To Track Hands, Track Pose, Detect Face, Detect Contours (Shapes), Detect Cars, Detect Number Plate, Detect Smile, Detect Eyes, Control Volume Using Gesture, Read QR Codes And Create Face Mesh On Image/Video.
Home-page: UNKNOWN
Author: Abhimanyu Sharma
Author-email: speedcuberabhi@gmail.com
License: UNKNOWN
Keywords: python,machine-learning,mediapipe,deep-learning,tensorflow
Platform: UNKNOWN
Classifier: Programming Language :: Python :: 3
Classifier: Operating System :: MacOS :: MacOS X
Classifier: Operating System :: Microsoft :: Windows
Requires-Dist: opencv-python
Requires-Dist: mediapipe
Requires-Dist: msvc-runtime
Requires-Dist: pycaw
Requires-Dist: comtypes
Requires-Dist: qrcode
Requires-Dist: numpy
